[{"timestamp":1628134771784,"files":[{"filename":"bundle.ae2eb.css","previous":445,"size":0,"diff":-445},{"filename":"bundle.*****.esm.js","previous":8400,"size":13779,"diff":5379},{"filename":"polyfills.*****.esm.js","previous":2180,"size":2180,"diff":0},{"filename":"route-home.chunk.291b3.css","previous":75,"size":75,"diff":0},{"filename":"route-home.chunk.*****.esm.js","previous":254,"size":254,"diff":0},{"filename":"route-notfound.chunk.4bc4b.css","previous":65,"size":65,"diff":0},{"filename":"route-notfound.chunk.*****.esm.js","previous":299,"size":299,"diff":0},{"filename":"route-profile.chunk.f7230.css","previous":78,"size":0,"diff":-78},{"filename":"route-profile.chunk.*****.esm.js","previous":1094,"size":0,"diff":-1094},{"filename":"sw-esm.js","previous":10735,"size":10854,"diff":119},{"filename":"bundle.fa6de.js","previous":8367,"size":0,"diff":-8367},{"filename":"polyfills.49cf4.js","previous":2178,"size":2178,"diff":0},{"filename":"route-home.chunk.cbb13.js","previous":257,"size":257,"diff":0},{"filename":"route-notfound.chunk.dc01a.js","previous":297,"size":297,"diff":0},{"filename":"route-profile.chunk.67077.js","previous":1098,"size":0,"diff":-1098},{"filename":"index.html","previous":1225,"size":1229,"diff":4},{"filename":"200.html","previous":833,"size":836,"diff":3},{"filename":"bundle.f9bf6.css","previous":0,"size":679,"diff":679},{"filename":"bundle.c3fd7.js","previous":0,"size":13864,"diff":13864}]},{"timestamp":1628130607480,"files":[{"filename":"ssr-build/ssr-bundle.dc3c7.css","previous":556,"size":0,"diff":-556},{"filename":"ssr-build/ssr-bundle.js","previous":4120,"size":0,"diff":-4120},{"filename":"bundle.ae2eb.css","previous":0,"size":445,"diff":445},{"filename":"bundle.*****.esm.js","previous":0,"size":8400,"diff":8400},{"filename":"polyfills.*****.esm.js","previous":0,"size":2180,"diff":2180},{"filename":"route-home.chunk.291b3.css","previous":0,"size":75,"diff":75},{"filename":"route-home.chunk.*****.esm.js","previous":0,"size":254,"diff":254},{"filename":"route-notfound.chunk.4bc4b.css","previous":0,"size":65,"diff":65},{"filename":"route-notfound.chunk.*****.esm.js","previous":0,"size":299,"diff":299},{"filename":"route-profile.chunk.f7230.css","previous":0,"size":78,"diff":78},{"filename":"route-profile.chunk.*****.esm.js","previous":0,"size":1094,"diff":1094},{"filename":"sw-esm.js","previous":0,"size":10735,"diff":10735},{"filename":"bundle.fa6de.js","previous":0,"size":8367,"diff":8367},{"filename":"polyfills.49cf4.js","previous":0,"size":2178,"diff":2178},{"filename":"route-home.chunk.cbb13.js","previous":0,"size":257,"diff":257},{"filename":"route-notfound.chunk.dc01a.js","previous":0,"size":297,"diff":297},{"filename":"route-profile.chunk.67077.js","previous":0,"size":1098,"diff":1098},{"filename":"index.html","previous":0,"size":1225,"diff":1225},{"filename":"200.html","previous":0,"size":833,"diff":833}]}]
